{
  "last_updated": "2025-09-11T15:46:05.505572",
  "export_date": "2025-09-11",
  "total_predictions": 5,
  "predictions": [
    {
      "model": "Algorand Model",
      "symbol": "ALGO-USD",
      "current_price": 0.241064,
      "predicted_price": 0.18395830893866436,
      "suggested_action": "SELL",
      "confidence": 52.54254288077336,
      "expected_return": -23.689016635140728,
      "prediction_date": "2025-09-11",
      "target_date": "2025-09-14"
    },
    {
      "model": "Long Bull Model V3.2",
      "symbol": "QQQ",
      "current_price": 580.7,
      "predicted_price": 569.2199560922714,
      "suggested_action": "STRONG SELL",
      "confidence": 63.247271981670046,
      "expected_return": -1.9769319627567667,
      "prediction_date": "2025-09-11",
      "target_date": "2025-09-21"
    },
    {
      "model": "QQQ Master Model",
      "symbol": "QQQ",
      "current_price": 580.7,
      "predicted_price": 570.8443087727865,
      "suggested_action": "SELL",
      "confidence": 95.0,
      "expected_return": -1.6972087527490238,
      "prediction_date": "2025-09-11",
      "target_date": "2025-09-12"
    },
    {
      "model": "QQQ Trading Signal",
      "symbol": "QQQ",
      "current_price": 580.7,
      "predicted_price": 583.7683410312981,
      "suggested_action": "OPEN LONG",
      "confidence": 56.085719777017104,
      "expected_return": 0.5283866077661474,
      "prediction_date": "2025-09-11",
      "target_date": "2025-09-14"
    },
    {
      "model": "Wishing Well QQQ Model",
      "symbol": "QQQ",
      "current_price": 580.7,
      "predicted_price": 619.231194433755,
      "suggested_action": "BUY",
      "confidence": 90.0,
      "expected_return": 6.635301262916306,
      "prediction_date": "2025-09-11",
      "target_date": "2025-09-16"
    }
  ],
  "system_status": "operational",
  "next_update": "15:40 ET daily"
}